explotest/__init__.py
explotest/explorer.py
explotest/helpers.py
explotest/meta_fixture.py
explotest/meta_test.py
explotest/test_builder.py
explotest/autoassert/__init__.py
explotest/autoassert/autoassert.py
explotest/autoassert/test_runner.py
explotest/ipy/__init__.py
explotest/ipy/extension.py
explotest/ipy/frontend.py
explotest/reconstructors/__init__.py
explotest/reconstructors/abstract_reconstructor.py
explotest/reconstructors/argument_reconstructor.py
explotest/reconstructors/pickle_reconstructor.py
explotest-1.0.4.dist-info/licenses/LICENSE
explotest-1.0.4.dist-info/METADATA
explotest-1.0.4.dist-info/WHEEL
explotest-1.0.4.dist-info/top_level.txt
explotest-1.0.4.dist-info/RECORD
