Metadata-Version: 2.4
Name: ExploTest
Version: 1.0.4
Summary: Automatically generate arguments of Python functions.
Author-email: Kevin Liu <kliu52@student.ubc.ca>, Randy Zhu <randyzhu@student.ubc.ca>
License-Expression: LGPL-3.0-or-later
Project-URL: Homepage, https://github.com/kliu04/explotest
Project-URL: Issues, https://github.com/kliu04/explotest/issues
Classifier: Programming Language :: Python :: 3
Classifier: Operating System :: OS Independent
Classifier: Development Status :: 3 - Alpha
Classifier: Natural Language :: English
Classifier: Topic :: Software Development :: Code Generators
Classifier: Topic :: Software Development :: Libraries :: Python Modules
Classifier: Topic :: Software Development :: Testing
Classifier: Topic :: Utilities
Requires-Python: >=3.13
License-File: LICENSE
Requires-Dist: dill
Requires-Dist: pytest
Provides-Extra: dev
Requires-Dist: black; extra == "dev"
Requires-Dist: flake8; extra == "dev"
Requires-Dist: pyright; extra == "dev"
Provides-Extra: test
Requires-Dist: ipython; extra == "test"
Requires-Dist: requests; extra == "test"
Requires-Dist: psycopg_c; extra == "test"
Requires-Dist: psycopg_binary; extra == "test"
Requires-Dist: pytest; extra == "test"
Requires-Dist: pytest-timeout; extra == "test"
Requires-Dist: pytest-mock; extra == "test"
Requires-Dist: numpy; extra == "test"
Requires-Dist: pandas; extra == "test"
Requires-Dist: coverage; extra == "test"
Requires-Dist: openai; extra == "test"
Requires-Dist: flask; extra == "test"
Requires-Dist: psycopg; extra == "test"
Provides-Extra: repl
Requires-Dist: ipython; extra == "repl"
Dynamic: license-file
